asynctasks/__init__.py
asynctasks/executionplan.py
asynctasks/executor.py
asynctasks-0.1.4.dist-info/DESCRIPTION.rst
asynctasks-0.1.4.dist-info/METADATA
asynctasks-0.1.4.dist-info/RECORD
asynctasks-0.1.4.dist-info/WHEEL
asynctasks-0.1.4.dist-info/metadata.json
asynctasks-0.1.4.dist-info/top_level.txt
asynctasks-0.1.4.dist-info/zip-safe
