Metadata-Version: 2.0
Name: asynctasks
Version: 0.1.4
Summary: Asynchronous task scheduler and runner for Python
Home-page: https://github.com/vramakin/asynctasks
Author: Ram
Author-email: vramak@gmail.com
License: MIT
Keywords: asyncio plan task scheduler async concurrent
Platform: UNKNOWN
Classifier: Programming Language :: Python :: 3.5
Classifier: Framework :: AsyncIO
